lnkd/__init__.py
lnkd/base.py
lnkd/dumper.py
lnkd/loader.py
lnkd/tag.py
lnkd/utils.py
lnkd-0.1.2.data/scripts/lnkd
lnkd-0.1.2.dist-info/LICENSE
lnkd-0.1.2.dist-info/METADATA
lnkd-0.1.2.dist-info/WHEEL
lnkd-0.1.2.dist-info/top_level.txt
lnkd-0.1.2.dist-info/RECORD
