Metadata-Version: 2.1
Name: lnkd
Version: 0.1.2
Summary: A simple utility for linked YAML files.
Home-page: UNKNOWN
Author: Mark Douthwaite
Author-email: mark@douthwaite.io
License: UNKNOWN
Platform: UNKNOWN
Requires-Dist: requests
Requires-Dist: pyyaml
Requires-Dist: fire
